easy_requests/__init__.py
easy_requests/__main__.py
easy_requests/cache.py
easy_requests/connections.py
easy_requests-1.1.2.dist-info/METADATA
easy_requests-1.1.2.dist-info/WHEEL
easy_requests-1.1.2.dist-info/licenses/LICENSE
easy_requests-1.1.2.dist-info/RECORD
