Metadata-Version: 2.4
Name: easy-requests
Version: 1.1.2
Summary: A Python library for simplified HTTP requests, featuring rate limiting, browser-like headers, and automatic retries. Built on the official `requests` library for reliability.
Project-URL: Homepage, https://github.com/hazel-noack/easy-requests
Project-URL: Issues, https://github.com/hazel-noack/easy-requests/issues
Author-email: Hazel Noack <hazel.noack@proton.me>
License-File: LICENSE
Classifier: Operating System :: OS Independent
Classifier: Programming Language :: Python :: 3
Requires-Python: >=3.10
Requires-Dist: requests~=2.32.4
